{"ajax":{"name":"ajax","desc":"","note":"","dep":[]},"anim":{"name":"anim","desc":"","note":"","dep":[]},"clone":{"name":["Clone"],"desc":["copies or clones an object"],"note":["a copy is a duplicate of the original; a clone overrides the original"],"dep":["stringify","parse"]},"event":{"name":"event","desc":"","note":"","dep":[]},"fade":{"name":"fade","desc":"","note":"","dep":[]},"parse":{"name":"parse","desc":"","note":"","dep":[]},"ready":{"name":"ready","desc":"","note":"","dep":["event"]},"stringify":{"name":"stringify","desc":"","note":"","dep":[]},"urlencode":{"name":"urlencode","desc":"","note":"","dep":[]}}